django_kickstart-0.1.6.dist-info/DESCRIPTION.rst
django_kickstart-0.1.6.dist-info/WHEEL
django_kickstart-0.1.6.dist-info/entry_points.txt
django_kickstart-0.1.6.dist-info/pydist.json
django_kickstart-0.1.6.dist-info/RECORD
django_kickstart-0.1.6.dist-info/top_level.txt
django_kickstart-0.1.6.dist-info/METADATA
django_kickstart-0.1.6.data/scripts/django-kickstart
django_kickstart/cli.py
django_kickstart/__init__.py
django_kickstart/template/Gemfile
django_kickstart/template/.gitignore
django_kickstart/template/CHANGELOG.txt
django_kickstart/template/README.md
django_kickstart/template/LICENSE.txt
django_kickstart/template/conf/apache_vhost.conf
django_kickstart/template/conf/.gitkeep
django_kickstart/template/pyenv/.gitkeep
django_kickstart/template/bin/.gitkeep
django_kickstart/template/docs/.gitkeep
django_kickstart/template/app/requirements.txt
django_kickstart/template/app/manage.py
django_kickstart/template/app/apps/project_name/views.py
django_kickstart/template/app/apps/project_name/settings.py
django_kickstart/template/app/apps/project_name/wsgi.py
django_kickstart/template/app/apps/project_name/__init__.py
django_kickstart/template/app/apps/project_name/urls.py
django_kickstart/template/app/apps/project_name/static/js/base.js
django_kickstart/template/app/apps/project_name/static/js/bootstrap.js
django_kickstart/template/app/apps/project_name/static/js/bootstrap/transition.js
django_kickstart/template/app/apps/project_name/static/js/bootstrap/carousel.js
django_kickstart/template/app/apps/project_name/static/js/bootstrap/button.js
django_kickstart/template/app/apps/project_name/static/js/bootstrap/affix.js
django_kickstart/template/app/apps/project_name/static/js/bootstrap/modal.js
django_kickstart/template/app/apps/project_name/static/js/bootstrap/popover.js
django_kickstart/template/app/apps/project_name/static/js/bootstrap/alert.js
django_kickstart/template/app/apps/project_name/static/js/bootstrap/dropdown.js
django_kickstart/template/app/apps/project_name/static/js/bootstrap/tab.js
django_kickstart/template/app/apps/project_name/static/js/bootstrap/tooltip.js
django_kickstart/template/app/apps/project_name/static/js/bootstrap/collapse.js
django_kickstart/template/app/apps/project_name/static/js/bootstrap/scrollspy.js
