Metadata-Version: 2.0
Name: django-kickstart
Version: 0.1.6
Summary: Tool for kickstarting django projects.
Home-page: https://github.com/theduke/django-kickstart
Author: Christoph Herzog
Author-email: chris@theduke.at
License: BSD License
Platform: UNKNOWN
Classifier: Environment :: Web Environment
Classifier: Framework :: Django
Classifier: Intended Audience :: Developers
Classifier: License :: OSI Approved :: BSD License
Classifier: Operating System :: OS Independent
Classifier: Programming Language :: Python
Classifier: Programming Language :: Python :: 2.6
Classifier: Programming Language :: Python :: 2.7
Classifier: Topic :: Internet :: WWW/HTTP
Classifier: Topic :: Internet :: WWW/HTTP :: Dynamic Content
Requires-Dist: Django (>=1.6)
Requires-Dist: virtualenv
